torchcontentareaext.cpython-39-x86_64-linux-gnu.so.pt110cu102
torchcontentareaext.cpython-39-x86_64-linux-gnu.so.pt110cu113
torchcontentareaext.cpython-39-x86_64-linux-gnu.so.pt111cu102
torchcontentareaext.cpython-39-x86_64-linux-gnu.so.pt111cu113
torchcontentareaext.cpython-39-x86_64-linux-gnu.so.pt112cu102
torchcontentareaext.cpython-39-x86_64-linux-gnu.so.pt112cu113
torchcontentareaext.cpython-39-x86_64-linux-gnu.so.pt112cu116
torchcontentareaext.cpython-39-x86_64-linux-gnu.so.pt19cu102
torchcontentareaext.py
torchcontentarea/__init__.py
torchcontentarea/_version.py
torchcontentarea/extension_wrapper.py
torchcontentarea/models/kernel_1_8.pt
torchcontentarea/models/kernel_2_8.pt
torchcontentarea/models/kernel_3_8.pt
torchcontentarea.libs/libcudart-45da57e3.so.11.6.55
torchcontentarea.libs/libcudart-80664282.so.10.2.89
torchcontentarea.libs/libcudart-a7b20f20.so.11.3.109
torchcontentarea-0.4.0.dist-info/LICENSE
torchcontentarea-0.4.0.dist-info/METADATA
torchcontentarea-0.4.0.dist-info/WHEEL
torchcontentarea-0.4.0.dist-info/top_level.txt
torchcontentarea-0.4.0.dist-info/RECORD
