Metadata-Version: 2.1
Name: torchcontentarea
Version: 0.4.0
Summary: A PyTorch tool kit for estimating the content area in endoscopic footage.
Home-page: https://github.com/charliebudd/torch-content-area
Author: Charlie Budd
Author-email: charles.budd@kcl.ac.uk
License: MIT
Platform: UNKNOWN
License-File: LICENSE
